odoo/addons/website_malaletra/__init__.py
odoo/addons/website_malaletra/__manifest__.py
odoo/addons/website_malaletra/data/__init__.py
odoo/addons/website_malaletra/data/images.xml
odoo/addons/website_malaletra/data/presets.xml
odoo/addons/website_malaletra/data/pages/edlp.xml
odoo/addons/website_malaletra/data/pages/hazte_amiga.xml
odoo/addons/website_malaletra/data/pages/home.xml
odoo/addons/website_malaletra/static/fonts/oswald/Oswald-Bold.ttf
odoo/addons/website_malaletra/static/fonts/oswald/Oswald-ExtraLight.ttf
odoo/addons/website_malaletra/static/fonts/oswald/Oswald-Light.ttf
odoo/addons/website_malaletra/static/fonts/oswald/Oswald-Medium.ttf
odoo/addons/website_malaletra/static/fonts/oswald/Oswald-Regular.ttf
odoo/addons/website_malaletra/static/fonts/oswald/Oswald-SemiBold.ttf
odoo/addons/website_malaletra/static/fonts/playfair_display/PlayfairDisplay-Black.ttf
odoo/addons/website_malaletra/static/fonts/playfair_display/PlayfairDisplay-BlackItalic.ttf
odoo/addons/website_malaletra/static/fonts/playfair_display/PlayfairDisplay-Bold.ttf
odoo/addons/website_malaletra/static/fonts/playfair_display/PlayfairDisplay-BoldItalic.ttf
odoo/addons/website_malaletra/static/fonts/playfair_display/PlayfairDisplay-ExtraBold.ttf
odoo/addons/website_malaletra/static/fonts/playfair_display/PlayfairDisplay-ExtraBoldItalic.ttf
odoo/addons/website_malaletra/static/fonts/playfair_display/PlayfairDisplay-Italic.ttf
odoo/addons/website_malaletra/static/fonts/playfair_display/PlayfairDisplay-Medium.ttf
odoo/addons/website_malaletra/static/fonts/playfair_display/PlayfairDisplay-MediumItalic.ttf
odoo/addons/website_malaletra/static/fonts/playfair_display/PlayfairDisplay-Regular.ttf
odoo/addons/website_malaletra/static/fonts/playfair_display/PlayfairDisplay-SemiBold.ttf
odoo/addons/website_malaletra/static/fonts/playfair_display/PlayfairDisplay-SemiBoldItalic.ttf
odoo/addons/website_malaletra/static/fonts/raleway/Raleway-Black.ttf
odoo_addon_website_malaletra-17.0.2.0.0.1.dist-info/METADATA
odoo_addon_website_malaletra-17.0.2.0.0.1.dist-info/WHEEL
odoo_addon_website_malaletra-17.0.2.0.0.1.dist-info/top_level.txt
odoo_addon_website_malaletra-17.0.2.0.0.1.dist-info/RECORD
