Metadata-Version: 2.1
Name: odoo-addon-website_malaletra
Version: 17.0.2.0.0.1
Requires-Python: >=3.10
Requires-Dist: odoo>=17.0a,<17.1dev
Summary: Malaletra theme
License: AGPL-3
Author: amoved | Luis H. Porras
Classifier: Programming Language :: Python
Classifier: Framework :: Odoo
Classifier: Framework :: Odoo :: 17.0
Classifier: License :: OSI Approved :: GNU Affero General Public License v3
